flashboard/__init__.py
flashboard/apps.py
flashboard/forms.py
flashboard/sites.py
flashboard/migrations/0001_initial.py
flashboard/migrations/0002_change_placeholder_namespace.py
flashboard/migrations/__init__.py
flashboard/templates/flashboard/scoreboard/base.html
flashboard/templates/flashboard/scoreboard/competition.html
flashboard/templates/flashboard/scoreboard/division.html
flashboard/templates/flashboard/scoreboard/index.html
flashboard/templates/flashboard/scoreboard/season.html
flashboard-0.4.1.dist-info/AUTHORS
flashboard-0.4.1.dist-info/LICENSE
flashboard-0.4.1.dist-info/METADATA
flashboard-0.4.1.dist-info/WHEEL
flashboard-0.4.1.dist-info/top_level.txt
flashboard-0.4.1.dist-info/RECORD
