Metadata-Version: 2.1
Name: flashboard
Version: 0.4.1
Summary: UNKNOWN
Home-page: https://bitbucket.org/fixja/flashboard
Author: Gary Reynolds
Author-email: gary@touch.asn.au
License: UNKNOWN
Platform: UNKNOWN
Requires-Dist: vitriolic[competition]
